[
  {
    "id": "introduction",
    "metadata": {
      "lang": "en",
      "section_title": "Introduction",
      "page_start": 1,
      "page_end": 1
    },
    "text": "X\nr\na  Circles UBI is a blockchain-based Community\nGermany in 2021, and designed to offer a U\ncontrol. Universal Basic Income is defined by\na periodic cash payment delivered to all ind\ncles UBI employs blockchain-based tokenizat\nparticipants in the form of a token named CR\nBlockchain technologies’ advancements al\ntems.  In particular, Ethereum facilitates the\n*\nPaper prepared for FRIBIS Conference Proceeding\n1\n\ned Universal Basic Income\n*\nrcles UBI currency\nessandro\n@protonmail.com\nLinares, Julio\ndu  jrlinares16@gmail.com\nSowelu\nanzo@unito.it\n, 2025\nract\nmunity Currency System (CCS) that has\ner 2021. The Circles Coop, which launched\nber 2023. In this paper, we show the results\nd November 2023. The questionnaire was\nto sevenmain sections: “Business Informa-\n”, “Knowledge and Perception of Circles”,\nomic position” and “Satisfaction”.  It was\nossible, combined with a semi-structured\npondents were twenty-five individuals in-\nork. The main emerging narrative points\ntivated by their identification with the val-\nCircles community. Among them, we se-\nce in type and degree of involvement. Fi-\ninkages that suggest a positive externality\nour knowledge, this is the first qualitative\nd as a community currency and adopting\ns a remarkable experiment for its adopted\nons. In fact, as far as we know, the integra-\nfeatures has been experimented with only\nelona, Spain) and none of them adopted a\ne try to outline strengths and weaknesses\nity. For this reason, future researchers and\nuable information.\n; blockchain; digital currency;\nCurrency System (CCS) launched in Berlin,\nniversal Basic Income independent of state\nThe Basic Income Earth Network (BIEN) as\nividuals unconditionally (Miller, 2020). Cir-\nion to provide an unconditional income to its\nC.\nlow for the creation of entire application sys-\ndecentralized execution of Turing-complete\ns 2023"
  },
  {
    "id": "methodology1",
    "metadata": {
      "lang": "en",
      "section_title": "Methodology",
      "page_start": 2,
      "page_end": 3
    },
    "text": "The Circles pilot is an open experiment and\ndemic control, characterized by specific parti\nexpenses, as observed in other studies on Uni\nnetwork has loose admission and participati\npants has been stable for most of the entire p\nmer of 2021 and later in 2023 (see Figure 1). H\n2\n\nment has significantly broadened the scope\novel category of software systems known as\n& Jacobsen, 2018).\ncles DApp, where participants receive their\ng them to spend it as a claim to goods and\nns between participants are established via\ngibility among personal currencies (Buterin,\not project launched by Circles Coop (Circles\nrlin between 2021 and 2023, where a subsidy\nconvert Circles tokens into national currency\nogram”. This program tried to address the\nt spend it in the economic network. In fact, it\ns tokens as amediumof payment, enhancing\ndelve into the impact of the Berlin pilot on\nhe qualitative counterpart to a prior quanti-\ninning Circles’ network (Avanzo, Criscione,\nanalysis methodologies.  Furthermore, em-\n(Rutherford, Collins, Morduch, & Ruthven,\nfive participants in the Circles project to gar-\nexperiences. The detailed survey responses\nmplete set of questions provided in the Ap-\nthe reduced sample size, we identified five\nn offer interesting insights into how Circles\nin the Berlin context. Some of these profiles\ntion data recorded in the blockchain, which\nhrough the interviews.\ninterest with a pragmatic and strategic ap-\nircles and similar pioneering projects in their\nit does not adhere to institutional or aca-\ncipation criteria and limitations on personal\nversal Basic Income (Standing, 2021). Circles’\non criteria and the number of active partici-\nroject’s duration with two peaks in the sum-\nence, the experiment’s open nature requires\n\nexamination within a comparably open resea\nat the nexus of innovative technologies and\nsingular case of a UBI pilot. Thus, we have op\nblending quantitative and qualitative method\nOur approach draws inspiration from ex\ncome (UBI), adapting the financial diaries app\ncles. Firstly, Circles’ conceptualization of Un\nContrary to conventional discussions that pr\nof state-centric interventions (Torry, 2019), C\nment capable of liberating currency from th\ninnovative experiments in the field, like the\nborg (Hornborg, 2017) and Recivita’s pioneer\nin Quatinga Velho, Brazil (Silva & de Almada\nThis perspective doesn’t positionUBI as a\ntool within a broader arsenal actively challen\nnial legacies (Adams & Abba, 2022). Within C\nestablishing a democratic money commons, t\nics (Linares &Cabaña, 2022). Beyond amere e\nsents the autonomy to reject relationships cha\nCircles theoretical frame must be kept in min\ninterpreting the manifold effects of Circles UB\nCircles UBI shares affinities with a comm\nprojects like Real Economy Currency (REC) in\n2021) or Mumbuca in Brazil (Cernev & Proenc\nblockchain and smart contracts to automate\nCircles UBI offers a unique case of study.\nThe financial diaries methodology underp\nCollins, Stuart Rutherford, and more first dev\nical method for comprehending the financia\npresenting the results in Rutherford et al. (200\nthe cash flows and decision-making processes\nmoney flows provide a tool to enhance our un\ndeal with low and often unpredictable income\nmultidimensional metrics as they provide a v\ninto specific groups of people, uncovering dy\nstatistics.\nIn our research, we adopted a repurposed\nspiration from it for the interviews and the pr\nThrough this method, we want to illuminat\nCircles on its recipients in Berlin. To achieve\nin CRC -i.e., the Circles token - within the bro\n3\n\nrch framework. Circles adopts a paradigm\nunorthodox monetary theories, making it a\nted for a hybrid analysis to assess its impact,\ns.\nisting scholarly work on Universal Basic In-\nroach to alignwith the unique context of Cir-\niversal Basic Income departs from the norm.\nedominantly situate UBI within the purview\nircles posits UBI as a transformative instru-\ne confines of state control, resonating with\ndual currency structure proposed by Horn-\ning work (Circles, Retrived on January 2024)\nLima, 2019).\nmerely economic policy but as amultifaceted\nging prevailing power structures and colo-\nircles project, UBI is framed as a catalyst for\nhereby disrupting traditional power dynam-\nconomic safety net, in this context, UBI repre-\nracterized by domination (Widerquist, 2013).\nd when making methodological choices and\nI on the lived experiences of its participants.\nunity currency system, similar to existing\nBarcelona (Belmonte, Puig, Roca, & Segura,\na, 2016). Yet, none of these projects leverages\nand decentralize the system.  In this regard,\nins the qualitative part of our research. Daryl\neloped financial diaries to provide an empir-\nl lives of low-income population segments,\n9) (Rutherford et al., 2009). The diaries track\nof individuals in a household over time. The\nderstanding of how people living in poverty\ns."
  },
  {
    "id": "methodology2",
    "metadata": {
      "lang": "en",
      "section_title": "Methodology",
      "page_start": 2,
      "page_end": 3
    },
    "text": "Financial diaries can complement existing\nery granular and locally comprehensive look\nnamics that might be hidden in nationwide\nversion of the financial diaries, drawing in-\nesentation of the results as personal profiles.\ne the effective impact of the UBI offered by\nthis, we contextualize the spending patterns\nader financial life of respondents, through a."
  },
  {
    "id": "results1",
    "metadata": {
      "lang": "en",
      "section_title": "Results",
      "page_start": 4,
      "page_end": 10
    },
    "text": "Circles blockchain system. The recent advan\nenabled researchers to conduct thorough emp\nble. The quantitative empirical examinations\nsignificantly bolster the resilience of local e\nLinares, 2022). Blockchain’s abundance of dat\na valuable resource for research. The transpar\ncoupled with decentralized accessibility, offe\ndomains (Joseph, 2019). Such transparency ca\ndifferent actors in the blockchain space are w\nto tackle it (Dashyan, Kulkarni, Linares, & Sr\ntools have been proven to be valid for analyzi\nomy, we employed some of those techniques\n& Takes, 2023).\n3  Results\nThis section is dedicated to the main presen\nchallenges that unfolded during the interview\n3.1  Sample\nOur sample is composed of twenty-five indiv\ncles’ network. The biological sex distribution\nnon-reporting. The gender distribution with\nmale, and three gender non-conforming indiv\nof the impact of UBI interventions across dive\nThe national distribution of the interview\nof the city of Berlin. Italians constitute the lar\nfollowed by Germans with five participants\nspectives of Polish and US nationals, each co\nof individuals from Australia, Belarus, Brazi\nMexico, Peru, and Spain, with one represent\nvance of UBI interventions and their potenti\n4\n\ns.\nions divided into sevenmain sections: “Busi-\nnomic Network”, “Use of Circles”, “Knowl-\nts Participation”, “Socio-economic position”\november 2023,  the questionnaire was dis-\nhe questionnaire was combined with a semi-\n- where participants were invited to expand\nsions on their experiences and perceptions.\nth the analysis of payment data stored in the\ncement of payment system digitization has\nirical studies that were previously impossi-\nof digital community currency systems could\nconomies (Criscione, Guterman, Avanzo, &\na, often stored publicly and openly, makes it\nency and immutability of blockchain records,\nr researchers unique insights across various\nn also be considered an issue for privacy and\norking with privacy-enhancing technologies\nikanth, 2023). Since these network analytical\nng highly granular data pools of a local econ-\nto examine these data (Mattsson, Criscione,\ntation of the results of the survey and the\nprocess.\niduals involved in various ways in the Cir-\nincludes nine female, five male, and eleven\nin the sample revealed twelve female, eight\niduals, providing a nuanced understanding\nrse gender identities.\ned sample mirrors the cosmopolitan nature\ngest national group, with six representatives,\n.  The sample further encompasses the per-\nntributing two interviewees. The inclusion\nl, Britain, Canada, the Netherlands, France,\native each, highlights the international rele-\nal impact on migrant communities. From a\n\ndemographic point of view, we interviewed s\ntheir twenties, and one in their forties. The\nolder is 41 years old.\nWithin the Circles’ system, two different k\nShared accounts. This distinction is reflected in\npolicy associated with it. Individual accounts a\nlet, Retrived on January 2024) that holds their\nwith a single, verified identity. These are th\nBasic Income once the verification process is\noriginal Safe contracts developed further to b\nated by single participants and other participa\naccounts don’t issue basic income.  In the Be\nbusinesses to transact in CRC.\nThis is the nature of the Individual / Busi\nflected in the questionnaire. Moreover, the\ninvolved in the Subsidy Program, the aforem\npand the reach of the pilot. This element fur\naccounts and the different experiences of the\ntionnaire proposed two parallel sets of ques\ndividual account, a Shared one, or both. We i\nbusinesses, of which nine were also active wi\n3.2  Spending Patterns\nAn initial insight from the questionnaire con\nboth for businesses and individuals.  Eighte\nplaining how andwhy their usage changed ov\ntively as their usage remained constant and tw\ndifferent patterns among the seventeen answ\ndividuals reported a relevant increase in their\nparticipants, the increase in usage is often at\nvices available in the Circles marketplace (se\nCoop’s shutdown in late 2023, the Circles ne\nconversely, abandonment by various affiliate\nin the available products. The constant variati\nenriched selection for participants, leading to\nexpands.\nAdditionally, the reported variations are\nnetwork, where participants transitioned fro\nular and intentional utilization of their Circle\ngrowing understanding of the intricate natur\nof this community. Conversely, an equivalen\n5\n\neventeen individuals in their thirties, five in\nyoungest individual is 25 years old and the\ninds of accounts exist: Individual accounts and\nthe technical architecture and the monetary\nre associated with a Safe Smart Contract (Wal-\npersonal keys and is designed to be matched\ne accounts that issue the monthly Universal\ncompleted. Shared accounts are a fork of the\ne used as collective wallets. They can be cre-\nnts can associate with them."
  },
  {
    "id": "results2",
    "metadata": {
      "lang": "en",
      "section_title": "Results",
      "page_start": 4,
      "page_end": 10
    },
    "text": "These collective\nrlin pilot, Shared accounts have been used by\nness distinction in our research, which is re-\nsampled businesses in the Berlin pilot were\nentioned incentive system designed to ex-\nther distinguished the two possible kinds of\nCircles network members. Thus, our ques-\ntions if the person interviewed used an In-\nnterviewed fourteen individuals and eleven\nth an Individual account.\ncerns the fluctuations in participants’ usage,\nen participants answered affirmatively, ex-\ner time. Seven participants responded nega-\no participants did not answer. We discerned\ners that reported changing behaviors. Six in-\nusage of Circles tokens over time. For these\ntributed to the expansion of goods and ser-\ne Figure 2). From its launch in 2021 until the\ntwork in Berlin witnessed participation and,\nd shops. This fluctuation signified variations\non of products available in CRC results in an\nincreased token expenditure as the network\nreflective of a growing familiarity with the\nm an initially sporadic usage to a more reg-\ns tokens. This transition is highlighted by a\ne of the network and the varied composition\nt cohort of 10 respondents share experiences\n\nof decreased or variable token usage over tim\n• Technological and communication factors. S\nthe transaction system often discourage\nthe Telegram channel was considered a\nproducts’ availability and receive impo\nwas a systemic flaw impacting the netwo\nover time. The second communication\nTelegram channel with an Online Mark\n• Insufficient and/or irregular supply, such\nvices in the marketplace.\n• Geographical factors, namely the physica\nusage of Circles tokens. Given that ou\nmigrants, it seems plausible to assume\nspent longer or shorter periods outside\nfact may have had an effect on usage an\n• Subsidy program influence. Changes in\nfluence of the subsidy program. As me\nprogram affects spending patterns.\n• Demurrage policy (i.e., negative interest\nintroduced in June 2022, when the Cir\nThe interviewer mentioned this as a fac\n3.3  Consumption Behaviour\nAmong different goods, the category of “foo\nthe most sought-after one, as indicated by\nHealth services, handmade products, bike re\nparticipants’ preferences. By offering financia\nmay have influenced their purchasing habits.\nformer asks participants whether Circles allo\nnot have bought otherwise: twenty participan\nThe last question asked participants if they re\nfollowing their Circles experience. Fourteen\nperceived change in their consumption habits\nOne noticeable initial change is that nume\nthe definition of what falls into the Marxian\nspending on items like organic products, hea\nsages), pillows, and ceramics that might be\nerwise.  In this regard, we notice also how C\nbeyond the paradigm of scarcity (Angehr, 201\n6\n\ne. They point out the challenges listed below.\npecifically, the slowness and unreliability of\nd participants. Moreover, in the beginning,\ns a not-so-easy communication tool to check\nrtant notifications. The first technical issue\nrk’s operation, whichwas slightly improved\nissue was slowly solved by integrating the\netplace.\nas the periodic unavailability of desired ser-\nl distance from Berlin, had an impact on the\nr sample comprises 20% Germans and 80%\nthat the majority of respondents may have\nof Berlin than their German peers, and this\nd engagement with the system.\nspending habits were also related to the in-\nntioned, participation (or the lack of) in the\nrate).  Interview #25 brings up the changes\ncles’ token undertook a revaluation policy.\ntor in decreasing expenditure.\nd and beverages” prominently dominates as\ntwenty-one out of twenty-five respondents.\npairs, and clothing were also prominent in\nl help to its participants, the Circles network\nQuestions #24 and #25 survey this issue. The\nwed them to buy products that they would\nts replied positively and only five negatively.\ncognized a shift in their consumption habits\ninterviewed Circles participants expressed a\n; while eleven did not experience any change.\nrous participants observe Circles expanding\n“realm of necessity” (Sayers, 2011) enabling\nlth services (such as acupuncture and mas-\ndeemed non-essential or too expensive oth-\nircles fosters an idea of money that moves\n9).\n\nSecondly, this shift in consumption consi\npants and local businesses, fostering a sense\ninstance, participants point out that Circles\npurchase otherwise with Euros. Answer #24\nfluenced how to spend EUR for groceries and\na change and those who did not (Interview #\nnative economic network gave them new pe\nexchange, community in business” and the im\ninteractions.  Participants also expressed gra\nthrough Circles, the ability to treat themselve\nance between gains and expenditures. Furth\nhelp in incentivizing the consumption of pr\nscribed in previous research (Assini, 2022).\nThe interviews confirm the different mean\ndifferently (Linares & Cabaña, 2022)."
  },
  {
    "id": "results3",
    "metadata": {
      "lang": "en",
      "section_title": "Results",
      "page_start": 4,
      "page_end": 10
    },
    "text": "Within\nconfiguration, centered on the reproduction o\naccording to the famous Marx’s formula M-\nwhich fuels economic growth and resource e\nequality that affects capitalistic societies (Pike\ntion of the planet (Hickel & Kallis, 2019). A\naimed to reverse such process and to plan th\nGreco, 2009; Slater & Jenkins, 2016), which c\nsystems “that put money at the service of t\naround” (Angelis, 2017).  In terms of its scop\nCircles pilot project stood out as a commend\nthe monetary relationships.\nA different and somehow discrepant asp\nin response to both queries, specifically add\ncourage participants to maximize their CRC s\nrefer to the reevaluation of Circles and the in\native interest rate) that the Circles token has u\n2022). Until that point, the Circles system issu\nrate based on a general poverty line as defi\non January 2024). After the reform, the daily\neach hour of the day), for a total of 720 CRC\nmurrage was introduced in the system. “Dem\npre-programmed depreciation of the nomina\nterest, and it has been studied in the context\n2012). The Cooperative decided to issue a 7%\nfee on money, set against the constant issuan\nicy aimed to tackle possible hoarding of toke\n7\n\nsts of a greater connection between partici-\nof community and ethical consumption. For\nallows them to afford items they might not\npoints out how the experience in Circles in-\nfood. Generally, both interviewed who felt\n23) noticed how being part of such an alter-\nrspectives on issues such as “market, value,\nportance of having values-aligned economic\ntitude for the affordability of specific items\ns more, and a conscious effort to strike a bal-\nermore, the described change in habits can\noducts with lower carbon emissions, as de-\nings that money can assume when designed\ncapitalism, money is entrapped in a specific\nf capital through the means of commodities,\nC-M (Marx, 1885), and the interests’ system\nxtraction. The price to pay is the soaring in-\ntty & Saez, 2013) and the ecological destruc-\nccording to its founders, the Circles project\ne becoming-common of money (Dodd, 2014;\nan be simply described as a plural series of\nheir own existence, and not the other way\ne and following the interviews’ results, the\nable initial effort of local re-configuration of\nect related to the design of Circles surfaced\nressing the incentive system devised to en-\npending. By incentive systems, interviewees\ntroduction of a policy of demurrage (i.e., neg-\nndertaken since the end of May 2022 (Coop,\ned daily 8 CRC per participant, an issuance\nned by the Circles Coop Hickel (Retrieved\nrate became 24 CRC per day (representing\nper month. Additionally, a program of de-\nurrage” is a monetary policy for the built-in\nl value of a currency, similar to negative in-\nof Complementary Currencies (Godschalk,\nrate of demurrage that “acts like a parking\nce of UBI” (Coop, 2022). This change of pol-\nns and to direct a gradual redistribution of\n\nall CRC in the system over time, to avoid pyr\ncryptocurrency systems (Mukherjee, Larkin, &\nInterview #15 considered this mechanism\nof accumulation typical of market economies\na subtle pressure to buy things they might no\nmake Circles more \"convenient\" for their sh\ninstances of over-consumption noticed in pa\nterview also highlighted how the perceived p\nled to faster expenses. This issue contrasts s\nterns of consumption (Coote, 2021) but it has\nwhich is focused on local and sustainable bus\nover-consumption.\n3.4  Knowledge and Perception\nThis segment of the questionnaire investigate\nCircles initiative and what level of awarenes\nticipants. The first question asked how indiv\nfriends as the main source, five indicated coll\nthe MOOS community in Berlin (Moos, Retr\ncontacts were more functional than social me\nThe following pair of questions asked par\ninterest at first and in what they were more\nquestionnaire presented three main options,\nintegration. Participants could choose more\nThe first question’s results are the following\nas the main motivation to join Circles, fifteen\nmentioned blockchain. Moreover, a minorit\nvalues of equality and post-capitalism reson\nparticipated in Circles, the communitywasm\naspect, succeeded by UBI with nineteen men\nOther factors mentioned are again the anti-c\nthe Web of Trust protocol as an anti-sybil solu\nThe next question asked how participants\ning: the project was mainly perceived as a Un\nfollowed by fifteen mentions for “means of p\neleven for a “political tool”, five for a “marke\nasset”, one for a “store of value/saving tool”\nWe can notice the peculiar position of Ci\ntechnologies, Circles stands out as a unique ca\ntructure did not play a prominent role in attr\nto our interviews, interest in blockchain dimi\n8\n\namid-like schema accumulation, common in\nCorbet, 2021).\nas an interesting alternative to the necessity\n. On the other hand, Interview #12 observed\nt necessarily need, describing it as a way to\nop."
  },
  {
    "id": "results4",
    "metadata": {
      "lang": "en",
      "section_title": "Results",
      "page_start": 4,
      "page_end": 10
    },
    "text": "This observation aligns with occasional\nrticipants’ behavior; moreover, the same in-\nrecarity of the Berlin pilot throughout 2023\ntudies relating UBI programs to lower pat-\nto be contextualized within Circles’ offering,\ninesses, thus balancing possible dynamics of\nd people’s knowledge and perception of the\ns and involvement emerged among its par-\niduals got to know Circles: sixteen indicated\neagues, three social media, and one specified\nived on January 2024). Generally, personal\ndia promotion.\nticipants what aspects of Circles ignited their\ninterested at the time of the interviews. The\nnamely the community, UBI, or Blockchain\nthan one and/or indicate their preferences.\n: seventeen participants mentioned the UBI\nmentioned the community, and only seven\ny of interviewees pointed out how Circles’s\nated with their sparking interest. After they\nentioned twenty times as themost interesting\ntions and blockchain systems with only five.\napitalistic values and the implementation of\ntion.\nperceived Circles. The results are the follow-\niversal Basic Income with eighteenmentions,\nayment”, fourteen for “means of exchange”,\nting tool”, two for an “investment / financial\nand zero for a “fake coin”.\nrcles. Despite being powered by blockchain\nse where the innovative technological infras-\nacting the participants’ interests. According\nnished over the two years of the project, and\n\none participant expressed uncertainty about\ncome underscores that the innovative poten\naspiration to forge an alternative economic ci\nvation also highlights a fundamental aspect o\nviewed solely as trustless systems, they shou\nippi, Mannan, & Reijers, 2020). More specific\nmechanisms is contingent on the presence o\nilant community that supports and upholds\nPutnam’s concept of social capital (Häuberer,\ncommunity depend on the bonds, trust, and\ncess of projects like Circles depends not only\nthe strength of the social bonds and networks\nDiverse perceptions translated into differe\nIn response to the question about participati\nconfirmed their involvement, while four ind\ninto event attendance preferences, fourteen p\nket and the Assembly, seven exclusively eng\ndisclose their preference.\nFurther exploring the frequency of their e\nparticipating once per quarter, another eight\nproximately once per year, and four respond\nwhat kind of activities participants got invol\ntivity mentioned is the “purchase of goods”\nfriends” holds fourteen mentions, “participa\ntimes, “selling goods” is mentioned eleven t\nand finally, with ten mentions, we find the “in\npotential business partners” option.\nWe must notice how our sample was co\nthe “core groups” of the Pilot program in Be\nbusinesses and long-time participants. Cons\nbiased by this role. However, it is arguable tha\ndriver, emphasizing the importance of share\ncircuit. Money is the product of a set of so\nreconfiguration of it, the role of the totality of\nimportant.\nHowever, the degree of participation and\nhow Circles allowed for different degrees o\njoined passively the community, adopting th\nwithin the Circles systemwill be analyzed in\nSome of the qualitative observations are co\nsimilarity index (JSI) indicates how much sim\n9\n\nthe utility of blockchain in Circles. This out-\ntial of Circles lies in its community and the\nrcuit grounded in shared values. This obser-\nf blockchain technologies. Rather than being\nld be regarded as confidence machines (Fil-\nally, the reliability of blockchain computing\nf effective governance structures and a vig-\ntheir functionality. This aligns with Robert\n2011), where the strength and resilience of a\nshared values among its members. The suc-\non the technology they employ but also on\nthey create.\nnt levels of involvement among participants.\nng in Circles events, twenty-one individuals\nicated a negative response. Delving deeper\narticipants typically attended both the Mar-\naged in the Market, and four chose not to\nvent attendance, eight interviewees reported\nattended once per month, five engaged ap-\nents opted not to respond. Then, we asked\nved in during Circles’ events. The main ac-\nwith seventeen mentions, “looking for new\ntion at the assembly” is mentioned twelve\nimes (as we interviewed eleven businesses)\ncrease your trust network / looking for new\nmposed of what may be defined as one of\nrlin - composed mostly of many associated\nequently, the nature of their participation is\nt the community aspect emerged as a central\nd values in constructing a parallel economic\ncial relationships and to achieve a different\nsocial relationships (the community) is very\ninvolvement was also fluctuating, showing\nf participation, as several participants only\ne role of “aleUBI recipients”. This position\nSection Casual Participants.\nrroborated by network analysis. The Jaccard\nilar two sets are."
  },
  {
    "id": "results5",
    "metadata": {
      "lang": "en",
      "section_title": "Results",
      "page_start": 4,
      "page_end": 10
    },
    "text": "It is calculated by the ratio\n\nbetween their intersection set over their unio\nsenders and receivers of Circles for each inter\nIn Figure 4, it is possible to observe that\ncate that businesses used to create trust conn\n5, it is possible to observe that JSI is higher\nnon-business participants used to create trust\ngoods and services in Circles.\nConcluding, this reflects the heterogeneit\nsome of the businesses, Circles was perceived\nof the participants, Circles was mostly percei\nexchange\".\n3.5  Social Composition\nAnother relevant insight that emerged from\nof the sample. The first question of this sect\neconomic activity in terms of the amount of\nreflects the fundamental idea that time is the\nit will ultimately determine the path of hum\nquestionnaire, eighteen answers indicated w\ntime, two participants answered with a mix o\nthree interviewees are unemployed and curre\nThe following question asked what are t\nquestionnaire’s participants. We found a div\nentrepreneurs/founders, four in marketing an\nhealth sector, two IT specialists, one admin\nsigner, and one bike mechanic and seller. W\nferent professions such as \"writer and facilitat\nmentation expert, herbalist and educator\", an\nfacilitator, organizer”. With the exception of t\nprofessionals in the tertiary sector.\nAmong business owners, seven do not h\nemploy freelancers and one who employs in\neach, two a dozen, one has four employees an\ncompanies as micro and small companies, a\nCommission (SME, Retrived on January 2024\nThe final question of this section asked the\nanswers are shown in Figure 3. Despite the l\ninto the income diversity of Circles’ network\n€\nin 2022 amounted to  15,000 for a “single per\nmedian annual income in 2023, in the Land\nour sample has one individual below the nat\n10\n\nn set. We considered the similarity between\nviewee and their trusted connections.\nJSI is higher for businesses. This may indi-\nections mostly with their clients.  In Figure\nfor non-businesses. This may indicate that\nconnections mostly with businesses offering\ny in perception observed in the survey. For\nalso as a \"marketing tool\". While for some\nved as a \"means of payment\" and \"means of\nthe survey section is the social composition\nion asked what was the interviewees’ main\ntime in the past six months. This approach\nultimate, fundamental scarce resource and\nan activities (Juster & Stafford, 1990).  In our\nage labor as their main activity in terms of\nf self-employment activities and housework,\nntly preparing for work, and one is a student.\nhe main current or past occupations of the\nerse array of working specializations:  four\nd communication, three professionals in the\nistrative and financial professional, one de-\ne also have four interviewees who have dif-\nor\", \"freelance artist and social worker\", \"fer-\nd “artist, researcher, cook, activist, producer,\nhe one bike mechanic, all the participants are\nave waged employees,  including two who\nterns, two companies count two employees\nd one has one. These rank all the interviewed\nccording to the indication of the European\n).\nparticipants their gross income per year. The\nimited sample, these data give us a glimpse\n.  In Germany, the yearly poverty threshold\nson household” (Bundesamt, 2023), and the\n€\nof Berlin, is  43.179 (Stepstone, 2023). Thus,\nional poverty threshold and two individuals."
  },
  {
    "id": "profiles1",
    "metadata": {
      "lang": "en",
      "section_title": "Profiles",
      "page_start": 11,
      "page_end": 15
    },
    "text": "In the course of our qualitative analysis, we id\nCircles, both individuals and businesses. Thes\nimpact that the project had.\n4.1  Unemployment\nMaria (Interview #24, name is fictional) is a\nmiddle-class family living in the North-East o\ntermittently since 2017, jugglingwork and pu\nto Circles came in the spring of 2022 through\nmediately drawn to the project’s concept—a U\nshe had heard about. Being well-educated an\nthe potential of Circles and became an active\nparticipating in the monthly market and shar\nDuring her first year in Circles, Maria w\na German fitness company, earning a middl\n11\n\nfall below the median annual income. Yet,\nrcles participation is observed. Nonetheless,\ncarious working conditions and unstable in-\nt comes to the forefront through the granular\nmentioned study led by Collins, for instance,\nmong participants was the irregular and un-\nrscores the critical importance of delving into\nling the challenges individuals grapple with\nt variability in their income streams.\ntered a series of challenges. Firstly, partici-\nrst challenge to complete the greater number\nan additional challenge revolved around the\nhe limited time frame of the interview. This\nof discussing one’s relationship with money\nd expenditure patterns. Another challenge\nrecall wrongly the terms of their participa-\nabout transactions and expenses. Finally, as\nhe operations of the Circles Coop maintain-\ning the affiliated enterprises, influenced the\nentified different categories of participants in\ne stories can help illuminate themultifaceted\n28-year-old Italian woman coming from a\nf Italy area. She has been living in Berlin in-\nrsuing her Master’s degree. Her introduction\na friend’s recommendation, and she was im-\nBI issued through an innovative technology\nd politically engaged, Maria quickly grasped\nmember of the Berlin community, frequently\ning her ideas in the subsequent Assembly.\norked part-time as a Marketing Manager in\n€\ne-class salary of 1500  per month, falling in\n\nthe lower segment of the middle class in th\nher purchasing power diminishing compared\nUkrainian War triggered inflation in German\nhelped her adjust her needs to the rising pr\ntoo expensive otherwise. This gradual shift i\nsupermarkets toward a local and more sustai\nA significant shift occurred in Maria’s Cir\ncorporate job in May 2023 and started receiv\nslosengeld II), Germany’s unemployment pa\nplus rent expenses). From this point, Maria be\non groceries, buying handmade products less\ngreater need, Maria felt that the Circles UBI p\nher quality of life. We quote here a relevant\npart of something that is taking care of me. Some\nactor that’s helping and taking care. Ensure me th\neat and I could afford quality products.\".\nSimultaneously, her unemployment cond\nMaria to give back to the Circles community\nin Circles, MIRA Upcycling Design, with com\ntasks—an ongoing collaboration at the time\nand the business agreed to compensate for thi\nmaking this arrangement happen in Circles’ a\nture of bureaucratic problems and the unexp\nMaria’s work remained voluntary. Lastly, M\ncles sparked a greater interest in UBI progra\nlaziness but rather active engagement.\nThe plot of the participant’s transactions (\npact that Circles had during Maria’s period\nand reaching its peak in September ’23. Com\nto rely more on Circles UBI system and her ou\nThere are three main takeaways from thi\nCircles UBI effectively supported an unemp\nof life during economically unstable times. T\nafter Maria became unemployed, with a focu\nSecondly, in Maria’s case, Circles successfully\nmajor food distributors in a big city, encour\neconomy. Finally, Maria’s active engagemen\nfundamental, community-centered nature of\nmunity as soon as her life conditions change\nand providing her the necessary free time to p\n12\n\ne country (OECD, 2021). However, she felt\nto her life in Italy, especially as the Russian-\ny. Maria found that participating in Circles\nices, enabling access to products that were\nn consumption habits led her away from big\nnable economic circuit.\ncles experience when she resigned from her\ning Bürgergeld (formerly known as Arbeit-\n€\nyment for adult job seekers ( 502 per month\ngan focusing her expenses in CRC primarily\nfrequently than before. During this period of\nrogram played a crucial role in maintaining\nabstract from her interview: \"I feel like being\none that’s not my parents or myself, but a third\nat also in difficult times I had something good to\nition provided more free time, prompting\n. She began assisting a local shop involved\nmunication and social media management\nof writing (December 2023).  Initially, Maria\ns work in CRC. Both sides were interested in\nlternative economic circuit. However, a mix-\nected closure of Circles stalled the deal, and\naria highlighted how her experience in Cir-\nms, showcasing that they do not incentivize\nsee Figure 6) corroborates the significant im-\nof unemployment, commencing in May ’23\npared to the previous period, Maria started\ntgoing transactions increased.\ns case."
  },
  {
    "id": "profiles2",
    "metadata": {
      "lang": "en",
      "section_title": "Profiles",
      "page_start": 11,
      "page_end": 15
    },
    "text": "Firstly, it serves as evidence of how\nloyed person in maintaining a good quality\nhis is demonstrated by the shift in expenses\ns on essential needs, particularly groceries.\ntransformed the standard relationship with\naging a shift toward a local and sustainable\nt in the Circles community underscores the\nCircles; the subject got involved in the com-\nd, giving Circles more relevance in her life\narticipate.\n\n4.2  Casual Participants\nAmong the interviewed participants, we ide\nticipants: what we may call “casual participan\nand #21 - are characterized by a steady expe\nin the community. Namely, two of them nev\nnot join any events. Moreover, none of these\nto the community. Yet, they expressed appre\nin the program and noted how Circles unlock\nthem. Also, they all expressed interest and ap\ncles. Therefore, these participants are aware o\nthe Circles network. Yet, they behave as pure\nconcern for the fate of the community that all\nThis fact can be read as evidence of the d\nthis type of economic initiative. When we d\ntions regarding participation in an economic\nCircles participants to grasp how a contribut\nUBI’s system. This underscores the extent to w\nintertwined with the notion of the State.\nThe difficulty for some Circles participa\ntween their contribution to the community a\ndicative of the entrenched imagery surround\nThe existence of a subsidy program for activ\nceived importance of individual contribution\nthe notion that as long as the subsidy progra\nwould endure. From this perspective, the Ci\npret a similar role to what the State usually d\nMoreover, the temporal dimension playe\nances of a Circles system required time, and\nlevel joined the platform between six month\nexpected cessation of the project in Berlin fur\nto become actively involved in the communi\nabrupt shutdown, added layers of uncertaint\ncomprehension of the Circles UBI experiment\nof this category of participants within Circle\nBerlin local pilot evolved, these \"casual partic\nA concluding observation: this category\nperiment like the one being examined, the un\npreted in a slightly nuanced manner. More pr\nto a lack of participation, a distinction that m\nexperiment.\n13\n\nntified an emerging category of Circles’ par-\nts”. These three profiles - interviews #8, #20,\nnditure of CRC but little or no involvement\ner participated in the Assembly and one did\nprofiles ever thought to contribute actively\nciation and gratitude for their participation\ned access to a new category of products for\npreciation for the community aspect of Cir-\nf the important role the community plays in\n\"recipients\" of an income program without\nowed this program to exist.\nifficulty of changing the imagery related to\necouple UBI from the state, certain assump-\nsystem are challenged. It was not easy for all\nion to the community was a contribution to\nhich the conceptualization of UBI is closely\nnts to fully comprehend the connection be-\nnd the functioning of the UBI system is in-\ning such socio-economic assistance models.\ne stores inadvertently downplayed the per-\ns, fostering a mindset that leaned towards\nm and the cooperative persisted, Circles UBI\nrcles Coop and its monetary decisions inter-\noes in such contexts.\nd a significant role. Understanding the nu-\nsuch participants with a lower engagement\ns and a year before the fall of 2023. The un-\nther curtailed opportunities for participants\nty. This temporal aspect, combined with the\nies to their engagement and obstacles to the\n. Various factors contributed to the existence\ns.  It is crucial to acknowledge that, as the\nipants\" played a significant role.\nunderscores how, in a community-based ex-\nconditionality feature of UBI must be inter-\necisely, unconditionality shouldn’t be linked\night exist in a State-based version of a UBI\n\n4.3  Business Case 1\nM. is a 39-year-old Brazilian-Italian woman\nnamed MIRA Design which designs and pro\n2006 in Curitiba, Brazil, in 2013 MIRA expand\nBangladesh’. MIRAmade in Bangladesh outs\nready-made garment industry (RMG) and brin\nin rural Rangpur, Northern Bangladesh. The\nwide through the website.\nMIRA’s relationship with Circles began\nShop. Their story is an example of how a sy\ntranslated from the real economy to the Circ\n2022, Eddie’s Shop, a member of the network\nin the store, accepting commissions for them.\nEUR and selling them both in EUR and CRC\n‘22, MIRA decided to actively join the Circles\nthe marketplace. Around the same months, E\nwithdrew from the Circles network due to the\nthis synergy from surviving within Circles.\nlinkages between Circles members has been\ntive. While the linkage between Eddie’s and M\na more successful linkage below.\nMIRA’s story in Circles is also insightful fo\nCircles network for three months before subse\nmost of the businesses involved, who have b\nning of their Circles experience."
  },
  {
    "id": "profiles3",
    "metadata": {
      "lang": "en",
      "section_title": "Profiles",
      "page_start": 11,
      "page_end": 15
    },
    "text": "In the shor\nresorting to the option of exchanging the CR\nimpact of the subsidy can be traced to the spi\nin Figure 7, when the subsidy program star\ntransactions can be explained by the fact that\nin EUR.\nFinally, MIRA also revealed the hurdles th\nwork while attempting to integrate Circles in\nin the interview was the limited availability o\nness activities within the Circles marketplace,\nutilize the currency. MIRA was looking for m\nskills on the market and it struggled to find t\nlation of CRC without sufficient opportunitie\nnotable exception of Maria’s case presented a\nor no time to explore the network’s offer, ev\nshutdown.\n14\n\nliving in Berlin.  She has a social business\nduces upcycled fashion items. Founded in\ned into Berlin with the line ‘Proudly made in\nources textile clippingwaste fromBangladesh’s\ngs them into the hands of the skilled craftswomen\nn, MIRA sells products in Berlin and world-\nthrough another local Berlin shop, Eddie’s\nnergy between businesses has been partially\nles currency system.  In the early months of\nsince 2021, started selling MIRA’s products\nEddie’s was purchasing MIRA’s products in\nwith success. For this reason, in the fall of\ncommunity and sell its products directly in\nddie’s Shop exited the subsidy program and\nunsustainability of the business, preventing\nThe idea of establishing network economic\na key strategic point of the Circles coopera-\nIRA stopped prematurely, we will examine\nr another reason: it was an active part of the\nquently joining the subsidy program, unlike\neen in the subsidy program since the begin-\nt term, the business sustained itself without\nC token for EUR, through the subsidy. The\nke of incoming transactions around April ‘23\nted. Also, the subsequent peak in outgoing\nMIRA’s owner started to exchange their CRC\nat it encountered during its period in the net-\nto its business model. A key issue revealed\nf desired services for fostering MIRA’s busi-\nhindering the business’s ability to effectively\narketing, graphic design, and video editing\nhem. This mismatch resulted in the accumu-\ns for expenditure (see Figure 8.  )  (with the\nbove). Moreover, MIRA’s owner found little\nen more so considering the abrupt project’s\n\n4.4  Business Case 2\nLocal Community Currency Systems can pr\nsmall and medium enterprises (Cepel, Kljuc\npositive impact has been evident in experim\nArgentina (Colacelli & Blackburn, 2005) and C\nlane, 2011). As revealed in the interview, th\npelling example within Circles, illustrating t\ngrowth of local businesses.\nQueerQuaff is a feminist and queer beer\nbootstrapped thanks to their participation in\nlearning,experimentation, solidarity and red\nproject’s founders first met in 2020 for an artis\nin Berlin growing out of the ruins of an East\ntwo found some wild hosp foraged there and\ntation. The idea gained traction, and the two\nproject (Hausproject) in Berlin known as H48\nteammet with members of the Circles cooper\nilar values.  The synergy resulted in an initi\nnew production, which allowed them to obta\nas a professional kitchen. This investment is\nBerlin and it precedes the establishment of th\ncrowdfunding accepting CRC tokens that then\nEuro. In this way, the bootstrap of a local bu\nmomentum.\n4.5  Economic Synergy\nAs stated previously, a key strategy to foster\nthe creation of economic linkages between bu\ndenote the intricate and reciprocal relationshi\nnomic entities within a given economic frame\nencompass both forward linkages, delineatin\nfrom initial production stages towards ultim\nwhich elucidate the dependencies on inputs o\ntors (Ten Raa, 2020). Through our interviews,\nlinkages through subsided partners in the ne\ncles, we focus on Business-to-Business interac\nto be effective in expanding production capab\ncollaborations.\nA significant linkage has been established\ntwo Berlin-based food and beverage business\nan authentic, handcrafted, and zero-waste foo\n15\n\novide a fertile ground for the flourishing of\nnikov, Kozubikova, & Krajcik, 2019).  This\nents conducted in various locations, such as\nanada (Wheatley, Younie, Alajlan, &McFar-\ne narrative of QueerQuaff serves as a com-\nhe tangible benefits of such systems for the\nproject based in Berlin, which activities got\nCircles.  It presents itself as “A space for\niscovery of feminist beer history”. The two\ntic residency in the Spreewald, a cultural hub\nGermany abandoned amusement park. The\ndecided to embark on the process of fermen-\nstarted producing a bigger batch in a house\n. Around the spring of 2021, QueerQuaff’s\native and they recognized in each other sim-\nal investment from Circles in QueerQuaff’s\nin their necessary means of production, such\namong the first in the history of the pilot in\ne subsidy program. QueerQuaff organized a\nwere exchanged through the cooperative in\nsiness helped the Circles network in gaining\nand expand the Circles network concerned\nsinesses in the network. Economic linkages\nps among diverse sectors, industries, or eco-\nwork (Hirschman, 1958)."
  },
  {
    "id": "profiles4",
    "metadata": {
      "lang": "en",
      "section_title": "Profiles",
      "page_start": 11,
      "page_end": 15
    },
    "text": "These connections\ng the directional flow of goods or services\nate consumption, and backward linkages,\nr rawmaterials provided by antecedent sec-\nwe noticed the emergence of several fruitful\ntwork. Specifically, within the context of Cir-\ntions. These relationships have been proven\nilities and increasing sales through business\nbetween RealRadix and FarmerConnection,\nes with a focus on sustainability. RealRadix is\nd company dedicated to reconnecting people."
  },
  {
    "id": "discussion",
    "metadata": {
      "lang": "en",
      "section_title": "Discussion",
      "page_start": 16,
      "page_end": 16
    },
    "text": "In this paragraph, we report the main critic\nCircles Coop and the related proposed soluti\nBerlin pilot shows that any autonomous group\nbottom up needs to be economically self-relia\nitself as a body that coordinates and expands\nThe experimental nature of Circles meant\nsubsidy and redemption system was suppose\negy was limited because Circles Cooop had n\nan unbalance between givers and receivers\nnumber of suppliers and their involvement w\n16\n\ntion is a local and sustainable enterprise that\nghboring Brandenburg region to Berlin.\nucts, they deal with green tomatoes, which,\nteristics, cannot be consumed directly. How-\nerConnection sought an innovative solution\nr the production of green tomato jam.  The\nnificant consumer of RealRadix’s products,\ngreen tomato jam, a result of this collabora-\nw available for sale and distribution through\nhis strategic partnership, mediated by CRC-\nallenge of food waste but also enhances the\nto be said, however, that FarmerConnection,\nlved in those kinds of strategic partnerships\n.\nthe Circles network involved a fermentation\ninted Life. As revealed in the interview with\nfted a personalized set of pottery plates and\nFood Magic’s culinary experiences and fer-\nwere utilized to enhance the overall dining\n. In return for these customized pieces, Food\nrrency). Subsequently, Tinted Life used these\nco-founder of Food Magic emphasized that\ngic vision, was also influenced by the abun-\nion to engage with the Circles community.\nto fortify the autonomy of the Circles eco-\nxchanging CRC into Euros, thereby fostering\nperating within Circles. Additionally, it alle-\nooperative’s subsidy program.\nal issues discussed in the last assemblies of\nons. The experience of Circles Coop and its\nwilling to implement basic income from the\nnt. In this way, it can continue to reproduce\nthe pilot.\na high risk for the businesses involved. The\nd to offset this risk. Nevertheless, this strat-\no secure revenue. One of the outcomes was\nin the Circles network.  In other words, the\nas insufficient for the creation of remarkable"
  },
  {
    "id": "conclusion1",
    "metadata": {
      "lang": "en",
      "section_title": "Conclusion",
      "page_start": 17,
      "page_end": 27
    },
    "text": "Our qualitative investigation of the impact o\nshed light on crucial facets of this unique b\na financial-diaries-inspired methodology, we\nparticipants, complementing previous quanti\ninsights.\nOur findings underscore the pivotal role o\nCircles project. Participants’ narratives consis\ninterpersonal dynamics, mutual support, and\nof Circles is deeply intertwined with the stren\nMoreover, we addressed the challenges p\nwithin the Circles system. While acknowled\nresilience and adaptability, demonstrating ho\nmitigated these challenges. This resilience n\nbut also provided valuable insights for future\nAn essential aspect illuminated through o\nand engagement within Circles. The decentr\nfor varying degrees of involvement, accomm\n17\n\nivator groups (CommunityActivation Teams,\nations.  In this way, Circles Coop could offer\nor low-interest rates. This financial service\ny trying to solve the issues of supply-chain\nayment of loans could give the cooperative\n-sharing model inspired by the principles of\nrative would invest in local businesses as a\nsubsidy program was inspired by economic\nindustrial capabilities in various countries\nionally in contrast with the more recent or-\nation of markets and privatisation of public\ned solutions could have allowed the cooper-\nthe form of a basic income. The adoption of\nccessful cases of Banco Palmas, Niteroi, and\nilva & de Almada Lima, 2019). Albeit these\nent support, for the organizers the prospect\nhicle for introducing basic income remained\nf the Berlin pilot on Circles participants has\nlockchain-based framework.  By employing\ndelved into the experiences of twenty-five\ntative analyses with narratives and nuanced\nf community as the driving force behind the\ntently highlighted the profound influence of\nshared values, revealing that the experience\ngth of its community.\nosed by technical instabilities and intricacies\nging these hurdles, participants showcased\nw the community effectively navigated and\not only emphasized the project’s robustness\niterations and similar endeavors.\nur study is the diverse levels of participation\nalized and open nature of the project allows\nodating participants with different prefer-\n\nences and comfort levels. This flexibility con\nindividuals with diverse needs and preferenc\nThe identification of five distinct profiles\ndynamic, namely the multifaceted impacts o\ndelineates a unique narrative, elucidating ho\ncategories of individuals and businesses in d\nstories of economic linkages suggest a path f\nrepurposed in future iterations.\nIn a broader sense, our study bridges aca\ngic outlook. By offering a comprehensive un\nprovide valuable insights for Circles and simi\nfuture trajectories. Our findings underscore t\nas community dynamics, technical challenges\ngible, varied impacts experienced by individu\nthese components will need to be considered\n\nCernev, A. K., & Proenca,  B. A.  (2016\ntal social currency in brazil / mumb\nbrasil.  GV Casos-Revista Brasileira d\nNA. Retrieved from https://link.g\n?u=anon~980ae254&sid=googleSc\n2024)\nChang, H.-J.  (2002). Kicking away the ladde\ncially in britain and the united states. C\nfrom http://www.jstor.org/stab\nCircles. (Retrived on January 2024). Recivitas\nCircles Cooperative. (Retrived on January 20\nColacelli, M., & Blackburn, D. (2005). Second\nof Monetary Economics, 56(3), 295–308.\n.1016/j.jmoneco.2009.02.002 d\nCoop, C. (2022). The revaluation of the circles s\nrevaluation-of-the-circles-system-c6eea7\nCoote, A. (2021, 01). Universal basic services\nScience, Practice and Policy, 17, 32-46. do\nCriscione, T., Guterman, E., Avanzo, S., & Lin\nBasic income, credit clearing, and reserve-b\ncussion Paper Series No. 04-2022). Frei\nfor Basic Income Studies (FRIBIS).\nDashyan, D., Kulkarni, A., Linares, J., & Srik\nmous trust and credit system. White Pap\nDodd, N. (2014). The social life of money. New\nFilippi, P. D., Mannan, M., & Reijers, W. (202\nproblem of trust & challenges of govern\n10.1016/j.techsoc.2020.101284\nGodschalk, H. (2012). Does demurragematter\nJournal of Community Currency Research,\nGreco, T.  (2009). The end of money and the fu\nPublishing.\nHickel, J.  (Retrieved on January 2024). Extre\nhttps://www.jasonhickel.org/blog/2021/3/28\nHickel, J., & Kallis, G. (2019, 04). Is green grow\ndoi: 10.1080/13563467.2019.1598964\nHirschman, A. O.  (1958). The strategy of econ\nUniversity Press New Haven.\nHornborg, A.  (2017). How to turn an ocean\nredesigning money for sustainability, ju\n10.2458/v24i1.20900\n1\n\n,  July-Dec.).  Mumbuca:  The first digi-\nuca:  A primeira moeda social digital do\ne Casos de Ensino em Administracao,  6(2),\nale.com/apps/doc/A666231115/IFME\nholar&xid=dbc77741  (Accessed 18 Jan.\nr: An unofficial history of capitalism, espe-\nhallenge, 45(5), 63–97. Retrieved 2024-01-19,\nle/40722165\n. https://www.recivitas.org/ .\n24). Circles. https://circles.coop/ .\nary currency: An empirical analysis. Journal\nRetrieved from https://dx.doi.org/10\noi: 10.1016/j.jmoneco.2009.02.002\nystem."
  },
  {
    "id": "conclusion2",
    "metadata": {
      "lang": "en",
      "section_title": "Conclusion",
      "page_start": 17,
      "page_end": 27
    },
    "text": "(https://circlesubi.medium.com/the-\n0e767d)\nand sustainable consumption. Sustainability:\ni: 10.1080/15487733.2020.1843854\nares, J.  (2022). Community currency systems:\nacked models and design principles (FRIBIS Dis-\nburg: Freiburg University, Freiburg Institute\nanth, K.  (2023). Circles entropy: An anony-\ner.\nJersey: Princeton University Press.\n0). Blockchain as a confidence machine: The\nance. Technology in Society, 62, 101284. doi:\nfor complementary currencies? International\n16(D), 58–69.\nture of civilization. Vermont: Chelsea Green\nme poverty isn’t natural, it is created (2021).\n/extreme-poverty-isnt-natural-it-is-created.\nth possible? New Political Economy, 25, 1-18.\nomic development / a.o. hirschman [Book]. Yale\nliner: A proposal for voluntary degrowth by\nstice, and resilience.  JPE, 24, 623–632. doi:\n9\n\nHäuberer, J. (2011). Introducing the civic pers\nconcept of social capital. In Social capita\ndoi: 10.1007/978-3-531-92646-9_3\nJoseph, B. K.  (2019,  June).  Blockchain fo\nderpinnings and Practice.  In M. P.\n(Eds.), Governance Models for Creating P\n175).  Springer.  Retrieved from https\n978-3-030-14446-3_8.html doi: 1\nJuster, F. T., & Stafford, F. P.  (1990).  The all\nmodels, and problems of measurement (IU\nResearch Institute of Industrial Econom\nLepinski, M., Micali, S., & Shelat, A. (2005). F\nof cryptography (pp. 245–263). Springer B\nLinares, J., & Cabaña, G. (2022). Towards an e\nstate. SOCIETY REGISTER, 6(3), 29-56.\nMarx, K. (1885). Capital (English Edition ed.,\nMattsson, C. E. S., Criscione, T., & Takes, F. W\ncurrency. Scientific Reports, 13(5864), e58\nMiller, A. (2020). A basic income handbook. Lua\nMoos. (Retrived on January 2024). Moos. http\nMukherjee, S., Larkin, C., & Corbet, S. (2021).\n(Ed.), Understanding cryptocurrency frau\n.1515/9783110718485-009\nOECD.  (2021).  Is the german middle class crum\nPublishing. doi: 10.1787/845208d7-en\nPiketty, T., & Saez, E. (2013). Top incomes an\npolicy implications. IMF Economic Revie\nRutherford, S., Collins, D., Morduch, J., & Rut\nworld’s poor live on 2 dollars a day. Princ\nfrom http://www.jstor.org/stab\nSayers, S.  (2011). Freedom and the ‘realm of\nPalgrave Macmillan. doi: 10.1057/9780\nSilva, M. O. D., & de Almada Lima, V. F.\nBrazil: From Bolsa Família to Pilot Exp\nNational: Mexico City and Basic Incom\nPalgrave International Handbook of Basic I\ntrieved from https://ideas.repec\n-4_16.html doi: 10.1007/978-3-030-2\nSlater, M., & Jenkins, T.  (2016). Credit com\nhttp://www.creditcommons.net.\nSME.  (Retrived on January 2024). Single mar\n2\n\npective on social capital – robert d. putnam’s\nl theory. VS Verlag für Sozialwissenschaften.\nr Open Data – Exploring Conceptual Un-\nR. Bolívar, K.  J. Bwalya, & C. G. Reddick\nublic Value in Open Data Initiatives (p. 161-\n://ideas.repec.org/h/spr/paitcp/\n0.1007/978-3-030-14446-3\nocation of time: Empirical findings, behavioural\nI Working Paper No. 258).  Stockholm: The\nics (IUI).\nair-zero knowledge. In J. Kilian (Ed.), Theory\nerlin Heidelberg.\ncology of care: Basic income after the nation-\ndoi: 10.14746/sr.2022.6.3.03\nVol. 2). London: Penguin Classics.\n. (2023). Circulation of a digital community\n64. doi: 10.1038/s41598-023-33184-1\nth Press Ltd.\ns://www.moos.space/ .\nCryptocurrency ponzi schemes. In S. Corbet\nd (Vol. 2, pp. 111–119). De Gruyter. doi: 10\nbling? risks and opportunities. Paris: OECD\nd the great recession: Recent evolutions and\nw, 61, 456–478. doi: 10.1057/imfer.2013.14\nhven, O. (2009). Portfolios of the poor: How the\neton University Press. Retrieved 2024-01-11,\nle/j.ctt7rzr4\nnecessity’.  In Marx and alienation. London:\n230309142_5\nS.  (2019,  June).  Citizen’s Basic Income in\neriments, with an Appendix: From Local to\ne, by Pablo Yanes.  In M. Torry (Ed.), The\nncome (p. 319-338). Palgrave Macmillan. Re-\n.org/h/pal/etbchp/978-3-030-23614\n3614-4\nmons: A model for the solidarity economy.\nket economy, european union. https://single-\n0\n\nmarket-economy.ec.europa.eu/smes/sme-defi\nStanding, G.  (2021). Basic income pilots: U\nIncome Studies, 16(1), 75–99. doi: 10.1515\nStepstone. (2023). Gehaltsreport 2023 (Tech. Re\nTen Raa, T. (2020). Linkages, fields of influen\ndoi: 10.1186/s40008-020-00210-8\nTorry, M. (2019). The palgrave international han\nMacmillan.\nWallet, S. (Retrived on January 2024). Safe wa\nWheatley, G., Younie, C., Alajlan, H., & McFa\nand social capital benefits. International\n84–89.  Retrieved from http://dx.\ndoi: 10.15133/j.ijccr.2011.009\nWiderquist, K. (2013). Independence, propertyle\nthe power to say no. New York: Springer.\nZhang, K., & Jacobsen, H.-A.  (2018). Towar\ntributed ledgers with blockchains.  In\ntributed computing systems (icdcs) (p. 133\n21\n\nnition_en.\nses, limitations and design principles. Basic\n/bis-2021-0021\np.). https://www.mcg-mm.de: Author.\nce and key sectors. Economic Structures, 9, 29.\ndbook of basic income. London, UK: Palgrave\nllet. https://safe.global/ .\nrlane, E.  (2011)."
  },
  {
    "id": "conclusion3",
    "metadata": {
      "lang": "en",
      "section_title": "Conclusion",
      "page_start": 17,
      "page_end": 27
    },
    "text": "Calgary dollars: Economic\nJournal of Community Currency Research, 15(1),\ndoi.org/10.15133/j.ijccr.2011.009\nssness, and basic income: A theory of freedom as\nds dependable, scalable, and pervasive dis-\n2018 ieee 38th international conference on dis-\n7-1346). doi: 10.1109/ICDCS.2018.00134\n\nFigures\nNumber of people se\n12000\n10000\n8000\n6000\n4000\n2000\n0\n20202021212121212121212121212122222222\nt v c n b r r y n l g p t v c n b r r \ncoeaeapauJuuecoeaeapa\nONDJFMAMJ ASONDJFMAM\nFigure 1: Number of participants\nTotal Transaction Volu\n700000\n600000\n500000\n400000\n300000\n200000\n100000\n0\n20202021212121212121212121212122222222\nt v c n b r r y n l g p t v c n b r r \ncoeaeapauJuuecoeaeapa\nONDJFMAMJ ASONDJFMAM\nFigure 2: Total transaction volu\n22\n\nnding Circles per month\n2222222222222222232323232323232323232323\ny n l g p t v c n b r r y n l g p t v c \nuJuuecoeaeapauJuuecoe\nJ ASONDJFMAMJ ASOND\nsending Circles units per month.\nme in Circles (per month)\n2222222222222222232323232323232323232323\ny n l g p t v c n b r r y n l g p t v c \nuJuuecoeaeapauJuuecoe\nJ ASONDJFMAMJ ASOND\nme in Circles units per month.\n\n2\nsr\ne\nw\ns\nn\nA \nf\no \nr1\ne\nb\nm\nu\nN\n0\n< 10,000  10,000-20,000 20,000-30,000 30,00\nIncom\nFigure 3: Income distributio\nJaccard Similarity Index betwe\n0.6\n0.5\n0.4\n0.3\n0.2\n0.1\n0.0\n2121 21 2122 22 2222 222222 22 2222\np  t  v  c  n  b  r  r  y  n  l  g  p  t \ne c o e a e a p a u Ju u e c o\nS O N D J F M A M J  A S O N\nFigure 4:  Jaccard Similarity Index between c\nfiles. In the case of non-business individuals,\nreceive Circles.\n23\n\n0-40,000 40,000-60,000 60,000-100,000  Uncertain/\nFluctuating\ne Range\nn among the interviewees.\nen clients and trust connections\nbusiness_1\nbusiness_2\nbusiness_3\nbusiness_4\nbusiness_5\nindividual_1\nindividual_2\n22 2223 23 2323 232323 23 2323 23 23\nv  c  n  b  r  r  y  n  l  g  p  t  v  c \ne a e a p a u Ju u e c o e\nD J F M A M J  A S O N D\nlients and trust connections of selected pro-\nclients are those fromwhom such individuals\n\nJaccard Similarity Index betwee\n1.0\n0.8\n0.6\n0.4\n0.2\n0.0\n2121 21 2122 22 2222 222222 22 2222\np  t  v  c  n  b  r  r  y  n  l  g  p  t \ne c o e a e a p a u Ju u e c o\nS O N D J F M A M J  A S O N\nFigure 5: Jaccard Similarity Index between su\nfiles. In the case of non-business individuals,\nsend Circles.\nTransaction Volume \n800\n700\n600\n500\n400\n300\n200\n100\n0\n22 22 22 22 22 22 23 23 23\nl   g   p   t   v   c  n   b   r \nJu  u  e  c  o  e a  e a  p\nA S O N D J  F M A\nFigure 6: Total amount of outgoing transaction\nunits per month.\n24\n\nn suppliers and trust connections\nbusiness_1\nbusiness_2\nbusiness_3\nbusiness_4\nbusiness_5\nindividual_1\nindividual_2\n22 2223 23 2323 232323 23 2323 23 23\nv  c  n  b  r  r  y  n  l  g  p  t  v  c \ne a e a p a u Ju u e c o e\nD J F M A M J  A S O N D\nppliers and trust connections of selected pro-\nsuppliers are those to whom such individuals\nIndividual Case (Maria)\nincoming\ntransactions\noutgoing\ntransactions\n23 23 23 23 23 23 23 23 23 24\nr   y  n   l   g   p   t   v   c  n \na u Ju  u  e  c  o  e a\nM J  A S O N D J\nsmade by Individual Case (Maria) inCircles\n\nNumber of Supplier\n8\n6\n4\n2\n0\n22  23  23  23  23  23\nc   n   b   r   r   y \ne  a  e  a  p  a  u\nD  J  F  M  A  M  J\nFigure 7: Number of suppliers of Busi\nTransaction Volum\n1750\n1500\n1250\n1000\n750\n500\n250\n0\n22  23  23  23  23  23  23\nc   n   b   r   r   y   n \ne  a  e  a  p  a  u\nD  J  F  M  A  M  J\nFigure 8: Total amount of transactions o\nAppendix\n1. User details\n1.1. Name, Surname, Circles Surname\n1.2.  Individual Wallet Address, Busine\n1.3. Phone Numbe, Age, Sex\n1.4. Gender, Nationality\n25\n\ns for Business Case 1\n23  23  23  23  23  23  23\nn   l   g   p   t   v   c \nJu  u  e  c  o  e\nA  S  O  N  D\nness 1 in Circles network per month.\ne Business Case 1\nincoming\ntransactions\noutgoing\ntransactions\n23  23  23  23  23  23  24\nl   g   p   t   v   c   n \nJu  u  e  c  o  e  a\nA  S  O  N  D  J\nf Business 1 in Circles units per month.\nss Wallet Address, Email Address\n\n1.5. Specific Information\n1.5.1. Within Circles network, are yo\n1.6. Business details\n1.6.1. What is your Business Name?\n1.6.2. What is your Business Addres\n1.6.3. What is your Business Sector C\n1.6.4. How long have you been part\n1.6.5. How often do you use Circles\n1.6.6. On average, howmuch do you\n2. Economic Network\n2.1. How long have you been part of C\n2.2. How often do you use Circles as in\n2.3. On average, howmuch do you spe\n2.4. Did your frequency of usage chan\nuser? If so, why?\n2.5. What do you use Circles for? Wha\nspecific as you can)\n2.6. Would you say you use Circles to\notherwise not buy? If so, in what?\n2.7. Would you say using Circles chang\n2.8. Do you share your Circles account\n2.9. Howmany people do you know in\n2.10. Where do you spend Circles?\n2.11. Do you use Circles more with busi\n2.12. Have you ever offered your own p\nmunity? If yes / not, why?\n2.13. Have you encountered instances\nproducts with CRC to resell in EUR\n2.14. Have you received any feedback fr\nmisuse of Circles within your ecos\n3. Knowledge & Perception of Circles\n3.1."
  },
  {
    "id": "conclusion4",
    "metadata": {
      "lang": "en",
      "section_title": "Conclusion",
      "page_start": 17,
      "page_end": 27
    },
    "text": "How did you know about Circles?\n3.2. What motivated you to join the Cir\n3.3. What part of Circles are you most\n3.4. Use of Circles\n26\n\nu an individual or a business?\ns?\node?\nof Circles as business?\nas business?\nspend in a month as business?\nircles as individual?\ndividual?\nnd in a month as individual?\nge across the time you have been a Circles\nt kind of goods you buy? (Be as broad and\nbuy products and services that you would\ned your habits of consumption?\nwith others?\nCircles?\nnesses or with private people?\nroducts and services within the Circles com-\nwhere Circles users appeared to have buy\n?\nom customers or other businesses regarding\nystem?\ncles Network?\ninterested in?\n\n3.4.1. How do you perceive Circles?\n3.5. How often do you use Circles as bu\n3.6. Did you take part in Circles’ event\n3.7. Circles Events Participation\n3.7.1. Which ones did you go?\n3.7.2. How often did you go?\n3.7.3. What do you do when joining\n3.8. Future of Circles\n3.8.1. Has your vision/opinion on C\ngram? How?\n3.8.2. What does it mean to you to b\n4. Socio-economic position\n4.1. Over the past six months, what wa\namount of time you spent on it?\n4.2. What is your past and/or current o\n4.3. Howmany employees does your co\n4.4. What is your gross income per yea\n4.5. Do you or your family own proper\n5. Satisfaction\n5.1. Howmuch do you feel satisfied ab\n5.2. Howmuch your general well-bein\nCIrcles UBI project?\n5.3. How likely would you recommend\n27\n\nsiness?\ns?\nthe Circles event?\nircles changed since you’re part of the pro-\ne a recipient of a basic income?\ns your main economic activity in terms of the\nccupation?\nmpany have? (for owners and self-employed)\nr in Euro?\nty?\nout the participation to Circles UBI project?\ng got improved thanks to the participation to\nthe participation to Circles UBI to a friend?."
  }
]